pytweezer/__init__ copy.py
pytweezer/__init__.py
pytweezer/beam.py
pytweezer/bsc.py
pytweezer/bscPmGauss.py
pytweezer/bscPointMatch.py
pytweezer/bsc_pm_gauss.py
pytweezer/bsc_point_match.py
pytweezer/error.py
pytweezer/find_equilibrium.py
pytweezer/force_torque.py
pytweezer/mentor.py
pytweezer/t_matrix.py
pytweezer/t_matrix_mie.py
pytweezer/beams/__init__.py
pytweezer/beams/beam.py
pytweezer/beams/gaussian.py
pytweezer/beams/point_match.py
pytweezer/beams/rotation.py
pytweezer/beams/translation.py
pytweezer/shapes/__init__.py
pytweezer/shapes/axi_sym_lerp.py
pytweezer/shapes/axi_sym_shape.py
pytweezer/shapes/cylinder.py
pytweezer/shapes/ellipsoid.py
pytweezer/shapes/shape.py
pytweezer/shapes/sphere.py
pytweezer/shapes/star_shape.py
pytweezer/shapes/stl_loader.py
pytweezer/shapes/super_ellipsoid.py
pytweezer/t_matrix/__init__.py
pytweezer/t_matrix/t_matrix.py
pytweezer/t_matrix/t_matrix_mie.py
pytweezer/utils/__init__.py
pytweezer/utils/_nb_anm_bnm_.py
pytweezer/utils/_nb_legendre_row_.py
pytweezer/utils/angular_grid.py
pytweezer/utils/combined_index.py
pytweezer/utils/compute_y_exp_minus_and_plus.py
pytweezer/utils/ka_nmax.py
pytweezer/utils/laguerre.py
pytweezer/utils/legendre_row.py
pytweezer/utils/match_size.py
pytweezer/utils/meshgrid.py
pytweezer/utils/n_max_2ka.py
pytweezer/utils/paraxial_beam_waist.py
pytweezer/utils/paraxial_transformation_matrix.py
pytweezer/utils/rotate_3x3tensor.py
pytweezer/utils/rotation_matrix.py
pytweezer/utils/rotations.py
pytweezer/utils/rtp2xyz.py
pytweezer/utils/rtpv2xyzv.py
pytweezer/utils/sbesselh.py
pytweezer/utils/sbesselj.py
pytweezer/utils/spharm.py
pytweezer/utils/sphere.py
pytweezer/utils/spherical_harmonics.py
pytweezer/utils/three_wide.py
pytweezer/utils/translate_z.py
pytweezer/utils/vsh.py
pytweezer/utils/vswf.py
pytweezer/utils/vswf_cart.py
pytweezer/utils/wigner_rotation_matrix.py
pytweezer/utils/xyz2rtp.py
pytweezer/utils/xyzv2rtpv.py
pytweezer/utils/polarizability/__init__.py
pytweezer-0.0.1.dist-info/LICENSE
pytweezer-0.0.1.dist-info/METADATA
pytweezer-0.0.1.dist-info/WHEEL
pytweezer-0.0.1.dist-info/top_level.txt
pytweezer-0.0.1.dist-info/RECORD
