Metadata-Version: 2.1
Name: pytweezer
Version: 0.0.1
Summary: short description here
Home-page: https://github.com/oscarkremer/pytweezer
Author: Oscar Schmitt Kremer
Author-email: oscar.s.kremer@hotmail.com
License: GNU GENERAL PUBLIC LICENSE
Classifier: Programming Language :: Python :: 3
Classifier: Operating System :: OS Independent
License-File: LICENSE
Requires-Dist: numpy
Requires-Dist: pytest
